{
  "project_info": {
    "project_number": "560359531737",
    "firebase_url": "https://test-31eca.firebaseio.com",
    "project_id": "test-31eca",
    "storage_bucket": "test-31eca.appspot.com"
  },
  "client": [
    {
      "client_info": {
        "mobilesdk_app_id": "1:560359531737:android:3fc812577c57a3b0",
        "android_client_info": {
          "package_name": "com.example.android.acmmobiletest"
        }
      },
      "oauth_client": [
        {
          "client_id": "560359531737-b3iea6mcklj700br1tjgbnfdims1ipg4.apps.googleusercontent.com",
          "client_type": 3
        }
      ],
      "api_key": [
        {
          "current_key": "AIzaSyBxffp6DXJssPwvFPb7TxGIgLP1yg_iaNE"
        }
      ],
      "services": {
        "analytics_service": {
          "status": 1
        },
        "appinvite_service": {
          "status": 1,
          "other_platform_oauth_client": []
        },
        "ads_service": {
          "status": 2
        }
      }
    }
  ],
  "configuration_version": "1"
}